odoo/addons/product_logistics_uom/README.rst
odoo/addons/product_logistics_uom/__init__.py
odoo/addons/product_logistics_uom/__manifest__.py
odoo/addons/product_logistics_uom/hooks.py
odoo/addons/product_logistics_uom/i18n/de.po
odoo/addons/product_logistics_uom/i18n/es.po
odoo/addons/product_logistics_uom/i18n/it.po
odoo/addons/product_logistics_uom/i18n/product_logistics_uom.pot
odoo/addons/product_logistics_uom/i18n/pt_BR.po
odoo/addons/product_logistics_uom/models/__init__.py
odoo/addons/product_logistics_uom/models/product_product.py
odoo/addons/product_logistics_uom/models/product_template.py
odoo/addons/product_logistics_uom/models/res_config_settings.py
odoo/addons/product_logistics_uom/readme/CONFIGURE.md
odoo/addons/product_logistics_uom/readme/CONTRIBUTORS.md
odoo/addons/product_logistics_uom/readme/CREDITS.md
odoo/addons/product_logistics_uom/readme/DESCRIPTION.md
odoo/addons/product_logistics_uom/readme/INSTALL.md
odoo/addons/product_logistics_uom/readme/USAGE.md
odoo/addons/product_logistics_uom/static/description/icon.png
odoo/addons/product_logistics_uom/static/description/index.html
odoo/addons/product_logistics_uom/tests/__init__.py
odoo/addons/product_logistics_uom/tests/test_product_logistics_uom.py
odoo/addons/product_logistics_uom/views/product.xml
odoo/addons/product_logistics_uom/views/res_config_settings.xml
odoo_addon_product_logistics_uom-18.0.1.1.0.dist-info/METADATA
odoo_addon_product_logistics_uom-18.0.1.1.0.dist-info/WHEEL
odoo_addon_product_logistics_uom-18.0.1.1.0.dist-info/top_level.txt
odoo_addon_product_logistics_uom-18.0.1.1.0.dist-info/RECORD
